AutoFeedback_grader/README.rst
AutoFeedback_grader/__init__.py
AutoFeedback_grader/_version.py
AutoFeedback_grader/conftest.py
AutoFeedback_grader/grade_ipynbs.py
AutoFeedback_grader/quicktest.py
AutoFeedback_grader/test_exercises.py
autofeedback_grader-0.3.dist-info/METADATA
autofeedback_grader-0.3.dist-info/WHEEL
autofeedback_grader-0.3.dist-info/entry_points.txt
autofeedback_grader-0.3.dist-info/top_level.txt
autofeedback_grader-0.3.dist-info/RECORD
