Metadata-Version: 2.4
Name: autofeedback_grader
Version: 0.3
Summary: Python package for grading AutoFeedback exercises
Author-email: Andrew Brown <andrew.brown@qub.ac.uk>
License: BSD-3-Clause
Project-URL: Homepage, https://github.com/autofeedback-exercises/exercises
Project-URL: Repository, https://github.com/autofeedback-exercises/exercises.git
Classifier: Development Status :: 2 - Pre-Alpha
Classifier: Natural Language :: English
Classifier: Programming Language :: Python :: 3
Classifier: Programming Language :: Python :: 3.7
Classifier: Programming Language :: Python :: 3.8
Classifier: Programming Language :: Python :: 3.9
Classifier: Programming Language :: Python :: 3.10
Classifier: Programming Language :: Python :: 3.11
Classifier: Programming Language :: Python :: 3.12
Requires-Python: >=3.7
Requires-Dist: AutoFeedback
Requires-Dist: canvas_selector
Requires-Dist: inquirer
Requires-Dist: pytest
Requires-Dist: jupyter
Requires-Dist: jupytext
Requires-Dist: pandas
Requires-Dist: tqdm
